aoc_data/__init__.py
aoc_data-0.0.1.dist-info/METADATA
aoc_data-0.0.1.dist-info/WHEEL
aoc_data-0.0.1.dist-info/licenses/LICENSE
aoc_data-0.0.1.dist-info/RECORD
