Metadata-Version: 2.4
Name: aoc-data
Version: 0.0.1
Summary: Real data to test your Advent of Code solutions
Project-URL: Changelog, https://github.com/bsoyka/aoc-data/releases
Project-URL: Source, https://github.com/bsoyka/aoc-data
Author-email: Ben Soyka <hello@bsoyka.me>
License-File: LICENSE
Classifier: Development Status :: 1 - Planning
Classifier: Intended Audience :: Developers
Classifier: License :: OSI Approved :: MIT License
Classifier: Natural Language :: English
Classifier: Programming Language :: Python
Classifier: Programming Language :: Python :: 3
Classifier: Programming Language :: Python :: 3.9
Classifier: Programming Language :: Python :: 3.10
Classifier: Programming Language :: Python :: 3.11
Classifier: Programming Language :: Python :: 3.12
Classifier: Programming Language :: Python :: 3.13
Requires-Python: >=3.9
